{
  "$schema": "https://developer.microsoft.com/json-schemas/fabric/item/report/definition/visualContainer/2.3.0/schema.json",
  "name": "efbd0d5e9f7ff6b45a15",
  "position": {
    "x": 275.1473136915078,
    "y": 0,
    "z": 0,
    "height": 720,
    "width": 1005.1299826689774,
    "tabOrder": 3000
  },
  "visual": {
    "visualType": "tableEx",
    "query": {
      "queryState": {
        "Values": {
          "projections": [
            {
              "field": {
                "Column": {
                  "Expression": {
                    "SourceRef": {
                      "Entity": "Pricing Comparison"
                    }
                  },
                  "Property": "gmax_runner_sharecode"
                }
              },
              "queryRef": "Pricing Comparison.gmax_runner_sharecode",
              "nativeQueryRef": "gmax_runner_sharecode"
            },
            {
              "field": {
                "Column": {
                  "Expression": {
                    "SourceRef": {
                      "Entity": "Pricing Comparison"
                    }
                  },
                  "Property": "price_time"
                }
              },
              "queryRef": "Pricing Comparison.price_time",
              "nativeQueryRef": "Count of price_time"
            },
            {
              "field": {
                "Column": {
                  "Expression": {
                    "SourceRef": {
                      "Entity": "Pricing Comparison"
                    }
                  },
                  "Property": "price_betfair"
                }
              },
              "queryRef": "Sum(Pricing Comparison.price_betfair)",
              "nativeQueryRef": "price_betfair"
            },
            {
              "field": {
                "Column": {
                  "Expression": {
                    "SourceRef": {
                      "Entity": "Pricing Comparison"
                    }
                  },
                  "Property": "price_m1_2"
                }
              },
              "queryRef": "Sum(Pricing Comparison.price_m1_2)",
              "nativeQueryRef": "price_m1_2"
            },
            {
              "field": {
                "Column": {
                  "Expression": {
                    "SourceRef": {
                      "Entity": "Pricing Comparison"
                    }
                  },
                  "Property": "diff_m1_2"
                }
              },
              "queryRef": "Sum(Pricing Comparison.diff_m1_2)",
              "nativeQueryRef": "diff_m1_2"
            },
            {
              "field": {
                "Column": {
                  "Expression": {
                    "SourceRef": {
                      "Entity": "Pricing Comparison"
                    }
                  },
                  "Property": "price_e1_2"
                }
              },
              "queryRef": "Sum(Pricing Comparison.price_e1_2)",
              "nativeQueryRef": "price_e1_2"
            },
            {
              "field": {
                "Column": {
                  "Expression": {
                    "SourceRef": {
                      "Entity": "Pricing Comparison"
                    }
                  },
                  "Property": "diff_e1_2"
                }
              },
              "queryRef": "Sum(Pricing Comparison.diff_e1_2)",
              "nativeQueryRef": "diff_e1_2"
            },
            {
              "field": {
                "Column": {
                  "Expression": {
                    "SourceRef": {
                      "Entity": "Pricing Comparison"
                    }
                  },
                  "Property": "price_v1_2"
                }
              },
              "queryRef": "Sum(Pricing Comparison.price_v1_2)",
              "nativeQueryRef": "price_v1_2"
            },
            {
              "field": {
                "Column": {
                  "Expression": {
                    "SourceRef": {
                      "Entity": "Pricing Comparison"
                    }
                  },
                  "Property": "diff_v1_2"
                }
              },
              "queryRef": "Sum(Pricing Comparison.diff_v1_2)",
              "nativeQueryRef": "diff_v1_2"
            }
          ]
        }
      },
      "sortDefinition": {
        "sort": [
          {
            "field": {
              "Column": {
                "Expression": {
                  "SourceRef": {
                    "Entity": "Pricing Comparison"
                  }
                },
                "Property": "price_time"
              }
            },
            "direction": "Ascending"
          }
        ],
        "isDefaultSort": true
      }
    },
    "objects": {
      "columnWidth": [
        {
          "properties": {
            "value": {
              "expr": {
                "Literal": {
                  "Value": "83.16929767683962D"
                }
              }
            }
          },
          "selector": {
            "metadata": "Sum(Pricing Comparison.price_m1_2)"
          }
        },
        {
          "properties": {
            "value": {
              "expr": {
                "Literal": {
                  "Value": "132.191632546237D"
                }
              }
            }
          },
          "selector": {
            "metadata": "Pricing Comparison.price_time"
          }
        },
        {
          "properties": {
            "value": {
              "expr": {
                "Literal": {
                  "Value": "126.0311958405546D"
                }
              }
            }
          },
          "selector": {
            "metadata": "Pricing Comparison.gmax_runner_sharecode"
          }
        },
        {
          "properties": {
            "value": {
              "expr": {
                "Literal": {
                  "Value": "68.95921192675125D"
                }
              }
            }
          },
          "selector": {
            "metadata": "Sum(Pricing Comparison.price_betfair)"
          }
        },
        {
          "properties": {
            "value": {
              "expr": {
                "Literal": {
                  "Value": "82.41938909786367D"
                }
              }
            }
          },
          "selector": {
            "metadata": "Sum(Pricing Comparison.diff_v1_2)"
          }
        },
        {
          "properties": {
            "value": {
              "expr": {
                "Literal": {
                  "Value": "94.56498845457472D"
                }
              }
            }
          },
          "selector": {
            "metadata": "Sum(Pricing Comparison.price_e1_2)"
          }
        },
        {
          "properties": {
            "value": {
              "expr": {
                "Literal": {
                  "Value": "105.41074025583092D"
                }
              }
            }
          },
          "selector": {
            "metadata": "Sum(Pricing Comparison.diff_e1_2)"
          }
        },
        {
          "properties": {
            "value": {
              "expr": {
                "Literal": {
                  "Value": "102.3431524996912D"
                }
              }
            }
          },
          "selector": {
            "metadata": "Sum(Pricing Comparison.price_v1_2)"
          }
        },
        {
          "properties": {
            "value": {
              "expr": {
                "Literal": {
                  "Value": "115.85094223112596D"
                }
              }
            }
          },
          "selector": {
            "metadata": "Sum(Pricing Comparison.diff_m1_2)"
          }
        }
      ],
      "values": [
        {
          "properties": {
            "backColor": {
              "solid": {
                "color": {
                  "expr": {
                    "FillRule": {
                      "Input": {
                        "Aggregation": {
                          "Expression": {
                            "Column": {
                              "Expression": {
                                "SourceRef": {
                                  "Entity": "Pricing Comparison"
                                }
                              },
                              "Property": "diff_m1_2"
                            }
                          },
                          "Function": 0
                        }
                      },
                      "FillRule": {
                        "linearGradient3": {
                          "min": {
                            "color": {
                              "Literal": {
                                "Value": "'#a1343c'"
                              }
                            },
                            "value": {
                              "Literal": {
                                "Value": "-1D"
                              }
                            }
                          },
                          "mid": {
                            "color": {
                              "Literal": {
                                "Value": "'#FFFFFF'"
                              }
                            }
                          },
                          "max": {
                            "color": {
                              "Literal": {
                                "Value": "'maxColor'"
                              }
                            },
                            "value": {
                              "Literal": {
                                "Value": "1D"
                              }
                            }
                          },
                          "nullColoringStrategy": {
                            "strategy": {
                              "Literal": {
                                "Value": "'asZero'"
                              }
                            }
                          }
                        }
                      }
                    }
                  }
                }
              }
            }
          },
          "selector": {
            "data": [
              {
                "dataViewWildcard": {
                  "matchingOption": 1
                }
              }
            ],
            "metadata": "Sum(Pricing Comparison.diff_m1_2)"
          }
        },
        {
          "properties": {
            "backColor": {
              "solid": {
                "color": {
                  "expr": {
                    "FillRule": {
                      "Input": {
                        "Aggregation": {
                          "Expression": {
                            "Column": {
                              "Expression": {
                                "SourceRef": {
                                  "Entity": "Pricing Comparison"
                                }
                              },
                              "Property": "diff_e1_2"
                            }
                          },
                          "Function": 0
                        }
                      },
                      "FillRule": {
                        "linearGradient3": {
                          "min": {
                            "color": {
                              "Literal": {
                                "Value": "'#6b2328'"
                              }
                            },
                            "value": {
                              "Literal": {
                                "Value": "-1D"
                              }
                            }
                          },
                          "mid": {
                            "color": {
                              "Literal": {
                                "Value": "'#FFFFFF'"
                              }
                            }
                          },
                          "max": {
                            "color": {
                              "Literal": {
                                "Value": "'maxColor'"
                              }
                            },
                            "value": {
                              "Literal": {
                                "Value": "1D"
                              }
                            }
                          },
                          "nullColoringStrategy": {
                            "strategy": {
                              "Literal": {
                                "Value": "'asZero'"
                              }
                            }
                          }
                        }
                      }
                    }
                  }
                }
              }
            }
          },
          "selector": {
            "data": [
              {
                "dataViewWildcard": {
                  "matchingOption": 1
                }
              }
            ],
            "metadata": "Sum(Pricing Comparison.diff_e1_2)"
          }
        },
        {
          "properties": {
            "backColor": {
              "solid": {
                "color": {
                  "expr": {
                    "FillRule": {
                      "Input": {
                        "Aggregation": {
                          "Expression": {
                            "Column": {
                              "Expression": {
                                "SourceRef": {
                                  "Entity": "Pricing Comparison"
                                }
                              },
                              "Property": "diff_v1_2"
                            }
                          },
                          "Function": 0
                        }
                      },
                      "FillRule": {
                        "linearGradient3": {
                          "min": {
                            "color": {
                              "Literal": {
                                "Value": "'#6b2328'"
                              }
                            },
                            "value": {
                              "Literal": {
                                "Value": "-1D"
                              }
                            }
                          },
                          "mid": {
                            "color": {
                              "Literal": {
                                "Value": "'#FFFFFF'"
                              }
                            }
                          },
                          "max": {
                            "color": {
                              "Literal": {
                                "Value": "'maxColor'"
                              }
                            },
                            "value": {
                              "Literal": {
                                "Value": "1D"
                              }
                            }
                          },
                          "nullColoringStrategy": {
                            "strategy": {
                              "Literal": {
                                "Value": "'asZero'"
                              }
                            }
                          }
                        }
                      }
                    }
                  }
                }
              }
            }
          },
          "selector": {
            "data": [
              {
                "dataViewWildcard": {
                  "matchingOption": 1
                }
              }
            ],
            "metadata": "Sum(Pricing Comparison.diff_v1_2)"
          }
        }
      ]
    },
    "visualContainerObjects": {
      "stylePreset": [
        {
          "properties": {
            "name": {
              "expr": {
                "Literal": {
                  "Value": "'Minimal'"
                }
              }
            }
          }
        }
      ]
    },
    "drillFilterOtherVisuals": true
  },
  "filterConfig": {
    "filters": [
      {
        "name": "72f59c8a4e474fc2d9cd",
        "field": {
          "Column": {
            "Expression": {
              "SourceRef": {
                "Entity": "Pricing Comparison"
              }
            },
            "Property": "gmax_runner_sharecode"
          }
        },
        "type": "Categorical"
      },
      {
        "name": "d5db8432d3341efaf397",
        "field": {
          "Column": {
            "Expression": {
              "SourceRef": {
                "Entity": "Pricing Comparison"
              }
            },
            "Property": "price_time"
          }
        },
        "type": "Categorical"
      },
      {
        "name": "657c450dd60cf71abfec",
        "field": {
          "Column": {
            "Expression": {
              "SourceRef": {
                "Entity": "Pricing Comparison"
              }
            },
            "Property": "price_m1_2"
          }
        },
        "type": "Advanced"
      },
      {
        "name": "f65a914f4f446850ccbe",
        "field": {
          "Column": {
            "Expression": {
              "SourceRef": {
                "Entity": "Pricing Comparison"
              }
            },
            "Property": "price_e1_2"
          }
        },
        "type": "Advanced"
      },
      {
        "name": "b9b8bee9994666ac1e3b",
        "field": {
          "Column": {
            "Expression": {
              "SourceRef": {
                "Entity": "Pricing Comparison"
              }
            },
            "Property": "price_v1_2"
          }
        },
        "type": "Advanced"
      },
      {
        "name": "36c4fa695cec773c405d",
        "field": {
          "Column": {
            "Expression": {
              "SourceRef": {
                "Entity": "Pricing Comparison"
              }
            },
            "Property": "diff_v1_2"
          }
        },
        "type": "Advanced"
      },
      {
        "name": "481bf2d134cf51a57775",
        "field": {
          "Column": {
            "Expression": {
              "SourceRef": {
                "Entity": "Pricing Comparison"
              }
            },
            "Property": "price_betfair"
          }
        },
        "type": "Advanced"
      },
      {
        "name": "07772d6c89cef2c192c0",
        "field": {
          "Column": {
            "Expression": {
              "SourceRef": {
                "Entity": "Pricing Comparison"
              }
            },
            "Property": "diff_m1_2"
          }
        },
        "type": "Advanced"
      },
      {
        "name": "94b374eb7bd595cc814e",
        "field": {
          "Column": {
            "Expression": {
              "SourceRef": {
                "Entity": "Pricing Comparison"
              }
            },
            "Property": "diff_e1_2"
          }
        },
        "type": "Advanced"
      }
    ]
  }
}